yawTtk/__init__.py
yawTtk/dialog.py
yawTtk/megawidget.py
yawTtk/yawTtk.py
yawTtk-1.0.4.dist-info/DESCRIPTION.rst
yawTtk-1.0.4.dist-info/METADATA
yawTtk-1.0.4.dist-info/RECORD
yawTtk-1.0.4.dist-info/WHEEL
yawTtk-1.0.4.dist-info/metadata.json
yawTtk-1.0.4.dist-info/top_level.txt
