Metadata-Version: 2.0
Name: yawTtk
Version: 1.0.4
Summary: yawTtk is a Python wrapper for Tile. It provides classes which allow the display, positioning and control of native look'n feel widgets.
Home-page: http://bruno.thoorens.free.fr
Author: Bruno THOORENS
Author-email: bruno.thoorens@free.fr
License: Copyright© 2006-2016, THOORENS Bruno, BSD licence
Download-URL: https://github.com/Moustikitos/yawTtk
Keywords: ttk,tile,wrapper
Platform: UNKNOWN
